{
  "headers": {
    "x-amz-request-id": "C6778F18248A93CB",
    "x-amz-version-id": "qxUlT2gMFeM0ToS.TdSahvnN_vn3h4mv",
    "accept-ranges": "bytes",
    "content-length": "37433",
    "cf-request-id": "0871c5c6ca0000fca5ab003000000001",
    "cf-ray": "62630beadcc6fca5-VIE",
    "etag": "\"90ca5a70411db1f9735b799bcf57bd57\"",
    "x-amz-id-2": "jqu5bdXHeSE9+9fiqjs6VGOphVkV9mrNJ1oDFBeSz5/XLMEBQCFkFThe+YojpY3S8KxU+kxwHxQ=",
    "cache-control": "public, max-age=31536000, immutable",
    "alt-svc": "h3-27=\":443\"; ma=86400, h3-28=\":443\"; ma=86400, h3-29=\":443\"; ma=86400",
    "access-control-allow-origin": "*",
    "cf-cache-status": "MISS",
    "report-to": "{\"endpoints\":[{\"url\":\"https:\\/\\/a.nel.cloudflare.com\\/report?s=ZAFpc%2F88InwTwQkOwCx7h9ATgKwV9%2B%2BnOPc4lx3QvjvBk8NTy7EAmazXqmbd1VaaCMV6dhhXJZJK5%2BxICQK5MGTHlvs1r4sm390%3D\"}],\"max_age\":604800,\"group\":\"cf-nel\"}",
    "last-modified": "Tue, 12 Jan 2021 10:47:01 GMT",
    "expect-ct": "max-age=604800, report-uri=\"https://report-uri.cloudflare.com/cdn-cgi/beacon/expect-ct\"",
    "vary": "Accept-Encoding",
    "content-type": "application/typescript; charset=utf-8",
    "set-cookie": "__cfduid=d27d06954b86a8855060230984f3ce0681614105325; expires=Thu, 25-Mar-21 18:35:25 GMT; path=/; domain=.deno.land; HttpOnly; SameSite=Lax; Secure",
    "date": "Tue, 23 Feb 2021 18:35:25 GMT",
    "nel": "{\"max_age\":604800,\"report_to\":\"cf-nel\"}",
    "server": "cloudflare"
  },
  "url": "https://deno.land/x/mimetypes@v1.0.0/src/mime.ts"
}